[{"idTitulo":"1667","id_libro":"66","capitulo":"2","versiculo":"1","titulo":"Predicaci\u00f3n al Cuerpo o Templo de Yo Soy en Efeso."},{"idTitulo":"1668","id_libro":"66","capitulo":"2","versiculo":"8","titulo":"Predicaci\u00f3n al Templo de Yo Soy en Esmirna."},{"idTitulo":"1669","id_libro":"66","capitulo":"2","versiculo":"12","titulo":"Predicaci\u00f3n al Templo de Yo Soy en P\u00e9rgamo."},{"idTitulo":"1670","id_libro":"66","capitulo":"2","versiculo":"18","titulo":"Predicaci\u00f3n al Templo de Yo Soy en Tiatira."}]