[{"idTitulo":"1088","id_libro":"11","capitulo":"16","versiculo":"1","titulo":"El profeta Jeh\u00fa exhorta a Baasa rey de Israel con juicio de Yo Soy."},{"idTitulo":"1090","id_libro":"11","capitulo":"16","versiculo":"8","titulo":"Reinado de Ela pastor y padre de Israel."},{"idTitulo":"1091","id_libro":"11","capitulo":"16","versiculo":"9","titulo":"Degradaci\u00f3n de los reyes y pastores que obstentan el liderazgo del pueblo de Israel. Conspiraci\u00f3n de Zimri contra Ela para reinar \u00a0y pastorear sobre Israel."},{"idTitulo":"1092","id_libro":"11","capitulo":"16","versiculo":"21","titulo":"El pueblo de Yo Soy Dios de Israel de mal en peor, ahora se auto erigen como reyes, l\u00edderes o pastores, cualquiera por inicativa propia."},{"idTitulo":"1093","id_libro":"11","capitulo":"16","versiculo":"29","titulo":"Reinado de Acab pastor y padre de Israel."}]