[{"id": "1", "seg": 1.98, "versiculo": ""}, {"id": "2", "seg": 2.88, "versiculo": ""}, {"id": "3", "seg": 6.912, "versiculo": "1"}, {"id": "4", "seg": 12.312, "versiculo": "2"}, {"id": "5", "seg": 6.588, "versiculo": "3"}, {"id": "6", "seg": 10.512, "versiculo": "4"}, {"id": "7", "seg": 14.94, "versiculo": "5"}, {"id": "8", "seg": 11.34, "versiculo": "6"}, {"id": "9", "seg": 7.92, "versiculo": "7"}, {"id": "10", "seg": 7.668, "versiculo": "8"}, {"id": "11", "seg": 16.92, "versiculo": "9"}, {"id": "12", "seg": 15.048, "versiculo": "10"}, {"id": "13", "seg": 7.668, "versiculo": "11"}, {"id": "14", "seg": 6.876, "versiculo": "12"}, {"id": "15", "seg": 5.58, "versiculo": "13"}, {"id": "16", "seg": 9.504, "versiculo": "14"}, {"id": "17", "seg": 10.44, "versiculo": "15"}, {"id": "18", "seg": 7.056, "versiculo": "16"}, {"id": "19", "seg": 5.616, "versiculo": "17"}, {"id": "20", "seg": 9.792, "versiculo": "18"}, {"id": "21", "seg": 4.752, "versiculo": ""}, {"id": "22", "seg": 6.624, "versiculo": "19"}, {"id": "23", "seg": 9.756, "versiculo": "20"}, {"id": "24", "seg": 9.18, "versiculo": "21"}, {"id": "25", "seg": 5.94, "versiculo": "22"}, {"id": "26", "seg": 10.8, "versiculo": "23"}, {"id": "27", "seg": 15.156, "versiculo": "24"}, {"id": "28", "seg": 8.532, "versiculo": "25"}, {"id": "29", "seg": 7.596, "versiculo": "26"}, {"id": "30", "seg": 9.684, "versiculo": "27"}, {"id": "31", "seg": 12.996, "versiculo": "28"}, {"id": "32", "seg": 8.928, "versiculo": "29"}, {"id": "33", "seg": 13.68, "versiculo": "30"}, {"id": "34", "seg": 12.06, "versiculo": "31"}, {"id": "35", "seg": 7.56, "versiculo": "32"}, {"id": "36", "seg": 6.372, "versiculo": "33"}, {"id": "37", "seg": 8.748, "versiculo": "34"}, {"id": "38", "seg": 17.388, "versiculo": "35"}, {"id": "39", "seg": 4.212, "versiculo": "36"}, {"id": "40", "seg": 9.18, "versiculo": "37"}, {"id": "41", "seg": 12.816, "versiculo": "38"}, {"id": "42", "seg": 7.92, "versiculo": "39"}, {"id": "43", "seg": 8.028, "versiculo": "40"}, {"id": "44", "seg": 10.692, "versiculo": "41"}, {"id": "45", "seg": 6.588, "versiculo": "42"}, {"id": "46", "seg": 9.648, "versiculo": "43"}, {"id": "47", "seg": 3.42, "versiculo": ""}, {"id": "48", "seg": 13.752, "versiculo": "44"}, {"id": "49", "seg": 18.576, "versiculo": "45"}, {"id": "50", "seg": 7.38, "versiculo": "46"}, {"id": "51", "seg": 11.484, "versiculo": "47"}, {"id": "52", "seg": 12.312, "versiculo": "48"}, {"id": "53", "seg": 9.648, "versiculo": "49"}]